loggerman/__init__.py
loggerman/logger.py
loggerman/protocol.py
loggerman/style.py
loggerman-0.1.1.dist-info/METADATA
loggerman-0.1.1.dist-info/WHEEL
loggerman-0.1.1.dist-info/top_level.txt
loggerman-0.1.1.dist-info/RECORD
