Metadata-Version: 2.4
Name: LoggerMan
Version: 0.1.1
Requires-Python: >=3.10
Requires-Dist: MDit<0.2,>=0.1
Requires-Dist: PySerials<0.2,>=0.1
Requires-Dist: ActionMan<0.2,>=0.1
Requires-Dist: ProtocolMan<0.2,>=0.1
Requires-Dist: ExceptionMan<0.2,>=0.1
Requires-Dist: pkgdata<0.2,>=0.1.2
Requires-Dist: pydantic
Requires-Dist: rich
